ecs_pattern/__init__.py
ecs_pattern/ecs.py
ecs_pattern-1.4.0.dist-info/METADATA
ecs_pattern-1.4.0.dist-info/WHEEL
ecs_pattern-1.4.0.dist-info/top_level.txt
ecs_pattern-1.4.0.dist-info/RECORD
