Metadata-Version: 2.4
Name: ecs-pattern
Version: 1.4.0
Summary: Implementation of the ECS pattern for creating games
Home-page: https://github.com/ikvk/ecs_pattern
Author: Vladimir Kaukin
Author-email: KaukinVK@ya.ru
License: Apache-2.0
Keywords: python3,python,ecs,pattern,architecture,games,gamedev
Classifier: Programming Language :: Python :: 3
Classifier: License :: OSI Approved :: Apache Software License
Classifier: Operating System :: OS Independent
Dynamic: author
Dynamic: author-email
Dynamic: classifier
Dynamic: description
Dynamic: description-content-type
Dynamic: home-page
Dynamic: keywords
Dynamic: license
Dynamic: summary
